requirements.txt
setup.py
django_active_required/__init__.py
django_active_required/views.py
django_active_required.egg-info/PKG-INFO
django_active_required.egg-info/SOURCES.txt
django_active_required.egg-info/dependency_links.txt
django_active_required.egg-info/requires.txt
django_active_required.egg-info/top_level.txt