Metadata-Version: 2.1
Name: django-active-required
Version: 2020.7.1
Summary: Django ActiveRequiredMixin - request.user.is_active==True required
Home-page: https://github.com/andrewp-as-is/django-active-required.py
License: Unlicense
Keywords: django active
Platform: UNKNOWN
Classifier: Framework :: Django
Classifier: License :: Public Domain
Classifier: Operating System :: OS Independent
Classifier: Programming Language :: Python :: 3
